apk_patchx/__init__.py
apk_patchx/cli.py
apk_patchx/exceptions.py
apk_patchx/services/__init__.py
apk_patchx/services/adb.py
apk_patchx/services/android_sdk.py
apk_patchx/services/apktool.py
apk_patchx/services/frida.py
apk_patchx/services/patch_dex.py
apk_patchx/services/patch_smali.py
apk_patchx/services/signing.py
apk_patchx/services/split_merge.py
apk_patchx/utils/__init__.py
apk_patchx/utils/core.py
apk_patchx/utils/manifest.py
apk_patchx/utils/py.typed
apk_patchx/utils/versions.py
apk_patchx-7.9.2025.8.dist-info/entry_points.txt
apk_patchx-7.9.2025.8.dist-info/licenses/LICENSE
apk_patchx-7.9.2025.8.dist-info/WHEEL
apk_patchx-7.9.2025.8.dist-info/METADATA
apk_patchx-7.9.2025.8.dist-info/RECORD
