Metadata-Version: 2.4
Name: apk-patchx
Version: 7.9.2025.8
Summary: Android APK manipulation toolkit with Frida gadget injection support
Keywords: android,apk,reverse-engineering,frida,patching
Author: APKPatcher Contributors
Requires-Python: >=3.8
Classifier: Development Status :: 4 - Beta
Classifier: Environment :: Console
Classifier: Intended Audience :: Developers
Classifier: License :: OSI Approved :: MIT License
Classifier: Operating System :: POSIX :: Linux
Classifier: Operating System :: MacOS
Classifier: Operating System :: Microsoft :: Windows
Classifier: Programming Language :: Python :: 3
Classifier: Programming Language :: Python :: 3.8
Classifier: Programming Language :: Python :: 3.9
Classifier: Programming Language :: Python :: 3.10
Classifier: Programming Language :: Python :: 3.11
Classifier: Programming Language :: Python :: 3.12
Classifier: Topic :: Security
Classifier: Topic :: Software Development :: Build Tools
Classifier: Topic :: System :: Software Distribution
License-File: LICENSE
Requires-Dist: click>=8.0.0
Requires-Dist: requests>=2.25.0
Requires-Dist: tqdm>=4.60.0
Requires-Dist: colorama>=0.4.4
Project-URL: Homepage, https://github.com/kaifcodec/apk-patchx
Project-URL: Issues, https://github.com/kaifcodec/apk-patchx/issues
Project-URL: Repository, https://github.com/kaifcodec/apk-patchx.git
